[
  {
    "İL": "AFYONKARAHİSAR",
    "İLÇE": "SULTANDAĞI",
    "MAHALLE": "DEREÇİNE, CUMHURİYET",
    "id": 1009
  },
  {
    "İL": "AFYONKARAHİSAR",
    "İLÇE": "SULTANDAĞI",
    "MAHALLE": "YILDIRIM",
    "id": 1010
  },
  {
    "İL": "AFYONKARAHİSAR",
    "İLÇE": "SULTANDAĞI",
    "MAHALLE": "YEŞİLÇİFTLİK, YILDIZ",
    "id": 1011
  },
  {
    "İL": "AFYONKARAHİSAR",
    "İLÇE": "SULTANDAĞI",
    "MAHALLE": "DEREÇİNE, KARAMAN",
    "id": 1012
  },
  {
    "İL": "AFYONKARAHİSAR",
    "İLÇE": "SULTANDAĞI",
    "MAHALLE": "KAYRAN",
    "id": 1013
  },
  {
    "İL": "AFYONKARAHİSAR",
    "İLÇE": "SULTANDAĞI",
    "MAHALLE": "PAZARALTI",
    "id": 1014
  },
  {
    "İL": "AFYONKARAHİSAR",
    "İLÇE": "SULTANDAĞI",
    "MAHALLE": "YEŞİLÇİFTLİK, AŞAĞI",
    "id": 1015
  },
  {
    "İL": "AFYONKARAHİSAR",
    "İLÇE": "SULTANDAĞI",
    "MAHALLE": "YEŞİLÇİFTLİK, TEPEBAŞI",
    "id": 1016
  },
  {
    "İL": "AFYONKARAHİSAR",
    "İLÇE": "SULTANDAĞI",
    "MAHALLE": "DEREÇİNE, KAVAKLI",
    "id": 1017
  },
  {
    "İL": "AFYONKARAHİSAR",
    "İLÇE": "SULTANDAĞI",
    "MAHALLE": "YEŞİLÇİFTLİK, YUKARI",
    "id": 1018
  },
  {
    "İL": "AFYONKARAHİSAR",
    "İLÇE": "SULTANDAĞI",
    "MAHALLE": "YEŞİLÇİFTLİK, AKPINAR",
    "id": 1019
  },
  {
    "İL": "AFYONKARAHİSAR",
    "İLÇE": "SULTANDAĞI",
    "MAHALLE": "DEREÇİNE, ATATÜRK",
    "id": 1020
  },
  {
    "İL": "AFYONKARAHİSAR",
    "İLÇE": "SULTANDAĞI",
    "MAHALLE": "DEREÇİNE, CAMİKEBİR",
    "id": 1021
  },
  {
    "İL": "AFYONKARAHİSAR",
    "İLÇE": "SULTANDAĞI",
    "MAHALLE": "SELÇUK",
    "id": 1022
  },
  {
    "İL": "AFYONKARAHİSAR",
    "İLÇE": "SULTANDAĞI",
    "MAHALLE": "YENİ",
    "id": 1023
  },
  {
    "İL": "AFYONKARAHİSAR",
    "İLÇE": "SULTANDAĞI",
    "MAHALLE": "YEŞİLÇİFTLİK, SIRA",
    "id": 1024
  },
  {
    "İL": "AFYONKARAHİSAR",
    "İLÇE": "SULTANDAĞI",
    "MAHALLE": "ÇAVUŞ",
    "id": 1025
  },
  {
    "İL": "AFYONKARAHİSAR",
    "İLÇE": "SULTANDAĞI",
    "MAHALLE": "YEŞİLÇİFTLİK, YENİKENT",
    "id": 1026
  },
  {
    "İL": "AFYONKARAHİSAR",
    "İLÇE": "ÇAY",
    "MAHALLE": "ORTA",
    "id": 1027
  },
  {
    "İL": "AFYONKARAHİSAR",
    "İLÇE": "ÇAY",
    "MAHALLE": "PAZARAĞAÇ, AFYON",
    "id": 1028
  },
  {
    "İL": "AFYONKARAHİSAR",
    "İLÇE": "ÇAY",
    "MAHALLE": "PAZARAĞAÇ, BEŞEVLER",
    "id": 1029
  },
  {
    "İL": "AFYONKARAHİSAR",
    "İLÇE": "ÇAY",
    "MAHALLE": "KÖPRÜBAŞI",
    "id": 1030
  },
  {
    "İL": "AFYONKARAHİSAR",
    "İLÇE": "ÇAY",
    "MAHALLE": "ALİ KALELİ",
    "id": 1031
  },
  {
    "İL": "AFYONKARAHİSAR",
    "İLÇE": "ÇAY",
    "MAHALLE": "AŞAĞI",
    "id": 1032
  },
  {
    "İL": "AFYONKARAHİSAR",
    "İLÇE": "ÇAY",
    "MAHALLE": "DEMİRAĞAÇ",
    "id": 1033
  },
  {
    "İL": "AFYONKARAHİSAR",
    "İLÇE": "ÇAY",
    "MAHALLE": "KARAMIKKARACAÖREN, AŞAĞI",
    "id": 1034
  },
  {
    "İL": "AFYONKARAHİSAR",
    "İLÇE": "ÇAY",
    "MAHALLE": "TEKKE",
    "id": 1035
  },
  {
    "İL": "AFYONKARAHİSAR",
    "İLÇE": "ÇAY",
    "MAHALLE": "İSTASYON",
    "id": 1036
  },
  {
    "İL": "AFYONKARAHİSAR",
    "İLÇE": "ÇAY",
    "MAHALLE": "PAZARAĞAÇ, YUKARI",
    "id": 1037
  },
  {
    "İL": "AFYONKARAHİSAR",
    "İLÇE": "ÇAY",
    "MAHALLE": "PAZARAĞAÇ, ORTA",
    "id": 1038
  },
  {
    "İL": "AFYONKARAHİSAR",
    "İLÇE": "ÇAY",
    "MAHALLE": "BAHÇELİEVLER",
    "id": 1039
  },
  {
    "İL": "AFYONKARAHİSAR",
    "İLÇE": "ÇAY",
    "MAHALLE": "KARAMIKKARACAÖREN, SEKA",
    "id": 1040
  },
  {
    "İL": "AFYONKARAHİSAR",
    "İLÇE": "ÇAY",
    "MAHALLE": "CEDİT",
    "id": 1041
  },
  {
    "İL": "AFYONKARAHİSAR",
    "İLÇE": "ÇAY",
    "MAHALLE": "DUMLUPINAR",
    "id": 1042
  },
  {
    "İL": "AFYONKARAHİSAR",
    "İLÇE": "ÇAY",
    "MAHALLE": "KARAMIKKARACAÖREN, YUKARI",
    "id": 1043
  },
  {
    "İL": "AFYONKARAHİSAR",
    "İLÇE": "ÇAY",
    "MAHALLE": "AKTAŞ",
    "id": 1044
  },
  {
    "İL": "AFYONKARAHİSAR",
    "İLÇE": "ÇAY",
    "MAHALLE": "ALİ İHSAN PAŞA",
    "id": 1045
  },
  {
    "İL": "AFYONKARAHİSAR",
    "İLÇE": "ÇAY",
    "MAHALLE": "KARAMIKKARACAÖREN, BAĞLAR",
    "id": 1046
  },
  {
    "İL": "AFYONKARAHİSAR",
    "İLÇE": "ÇAY",
    "MAHALLE": "ŞİRİNEVLER",
    "id": 1047
  },
  {
    "İL": "AFYONKARAHİSAR",
    "İLÇE": "ÇAY",
    "MAHALLE": "PAZARAĞAÇ, KARABULUT",
    "id": 1048
  },
  {
    "İL": "AFYONKARAHİSAR",
    "İLÇE": "ÇAY",
    "MAHALLE": "ELBİZ",
    "id": 1049
  },
  {
    "İL": "AFYONKARAHİSAR",
    "İLÇE": "ÇAY",
    "MAHALLE": "VAKIF",
    "id": 1050
  },
  {
    "İL": "AFYONKARAHİSAR",
    "İLÇE": "ÇAY",
    "MAHALLE": "YAKA",
    "id": 1051
  },
  {
    "İL": "AFYONKARAHİSAR",
    "İLÇE": "ÇAY",
    "MAHALLE": "YEŞİLEVLER",
    "id": 1052
  },
  {
    "İL": "AFYONKARAHİSAR",
    "İLÇE": "EVCİLER",
    "MAHALLE": "FATİH",
    "id": 1053
  },
  {
    "İL": "AFYONKARAHİSAR",
    "İLÇE": "EVCİLER",
    "MAHALLE": "CAMİKEBİR",
    "id": 1054
  },
  {
    "İL": "AFYONKARAHİSAR",
    "İLÇE": "EVCİLER",
    "MAHALLE": "KAYALIK",
    "id": 1055
  },
  {
    "İL": "AFYONKARAHİSAR",
    "İLÇE": "EVCİLER",
    "MAHALLE": "YUNUS EMRE",
    "id": 1056
  },
  {
    "İL": "AFYONKARAHİSAR",
    "İLÇE": "EVCİLER",
    "MAHALLE": "MEHMET AKİF",
    "id": 1057
  },
  {
    "İL": "AFYONKARAHİSAR",
    "İLÇE": "EVCİLER",
    "MAHALLE": "YAVUZ SELİM",
    "id": 1058
  },
  {
    "İL": "AFYONKARAHİSAR",
    "İLÇE": "KIZILÖREN",
    "MAHALLE": "CUMHURİYET",
    "id": 1059
  },
  {
    "İL": "AFYONKARAHİSAR",
    "İLÇE": "KIZILÖREN",
    "MAHALLE": "YENİ",
    "id": 1060
  },
  {
    "İL": "AFYONKARAHİSAR",
    "İLÇE": "ÇOBANLAR",
    "MAHALLE": "KARADEDE",
    "id": 1061
  },
  {
    "İL": "AFYONKARAHİSAR",
    "İLÇE": "ÇOBANLAR",
    "MAHALLE": "ZAFER",
    "id": 1062
  },
  {
    "İL": "AFYONKARAHİSAR",
    "İLÇE": "ÇOBANLAR",
    "MAHALLE": "BUCAK",
    "id": 1063
  },
  {
    "İL": "AFYONKARAHİSAR",
    "İLÇE": "ÇOBANLAR",
    "MAHALLE": "KOCAÖZ, ATATÜRK",
    "id": 1064
  },
  {
    "İL": "AFYONKARAHİSAR",
    "İLÇE": "ÇOBANLAR",
    "MAHALLE": "SIRAKAPI",
    "id": 1065
  },
  {
    "İL": "AFYONKARAHİSAR",
    "İLÇE": "ÇOBANLAR",
    "MAHALLE": "GÖLCÜK",
    "id": 1066
  },
  {
    "İL": "AFYONKARAHİSAR",
    "İLÇE": "ÇOBANLAR",
    "MAHALLE": "KOCAÖZ, CUMHURİYET",
    "id": 1067
  },
  {
    "İL": "AFYONKARAHİSAR",
    "İLÇE": "ÇOBANLAR",
    "MAHALLE": "KOCAÖZ,İSTİKLAL",
    "id": 1068
  },
  {
    "İL": "AFYONKARAHİSAR",
    "İLÇE": "ÇOBANLAR",
    "MAHALLE": "YAVUZ SELİM",
    "id": 1069
  },
  {
    "İL": "AFYONKARAHİSAR",
    "İLÇE": "ÇOBANLAR",
    "MAHALLE": "TERMALKENT",
    "id": 1070
  },
  {
    "İL": "AFYONKARAHİSAR",
    "İLÇE": "ÇOBANLAR",
    "MAHALLE": "IŞIK",
    "id": 1071
  },
  {
    "İL": "AFYONKARAHİSAR",
    "İLÇE": "ÇOBANLAR",
    "MAHALLE": "KOCAÖZ, FATİH",
    "id": 1072
  },
  {
    "İL": "AFYONKARAHİSAR",
    "İLÇE": "ÇOBANLAR",
    "MAHALLE": "YENİ",
    "id": 1073
  },
  {
    "İL": "AFYONKARAHİSAR",
    "İLÇE": "DAZKIRI",
    "MAHALLE": "ÇAMLIK",
    "id": 1074
  },
  {
    "İL": "AFYONKARAHİSAR",
    "İLÇE": "DAZKIRI",
    "MAHALLE": "ESENTEPE",
    "id": 1075
  },
  {
    "İL": "AFYONKARAHİSAR",
    "İLÇE": "DAZKIRI",
    "MAHALLE": "BARBAROS",
    "id": 1076
  },
  {
    "İL": "AFYONKARAHİSAR",
    "İLÇE": "DAZKIRI",
    "MAHALLE": "VEHBİ KOÇ SANAYİ BÖLGESİ",
    "id": 1077
  },
  {
    "İL": "AFYONKARAHİSAR",
    "İLÇE": "DAZKIRI",
    "MAHALLE": "YEŞİLYURT",
    "id": 1078
  },
  {
    "İL": "AFYONKARAHİSAR",
    "İLÇE": "DAZKIRI",
    "MAHALLE": "KURTULUŞ",
    "id": 1079
  },
  {
    "İL": "AFYONKARAHİSAR",
    "İLÇE": "DAZKIRI",
    "MAHALLE": "YENİYOL",
    "id": 1080
  },
  {
    "İL": "AFYONKARAHİSAR",
    "İLÇE": "BAYAT",
    "MAHALLE": "BÜYÜK",
    "id": 1081
  },
  {
    "İL": "AFYONKARAHİSAR",
    "İLÇE": "BAYAT",
    "MAHALLE": "CUMHURİYET",
    "id": 1082
  },
  {
    "İL": "AFYONKARAHİSAR",
    "İLÇE": "BAYAT",
    "MAHALLE": "HÜRRİYET",
    "id": 1083
  },
  {
    "İL": "AFYONKARAHİSAR",
    "İLÇE": "BAYAT",
    "MAHALLE": "YENİ",
    "id": 1084
  },
  {
    "İL": "AFYONKARAHİSAR",
    "İLÇE": "BAŞMAKÇI",
    "MAHALLE": "BARBAROS",
    "id": 1085
  },
  {
    "İL": "AFYONKARAHİSAR",
    "İLÇE": "BAŞMAKÇI",
    "MAHALLE": "AŞAĞI HİLAL",
    "id": 1086
  },
  {
    "İL": "AFYONKARAHİSAR",
    "İLÇE": "BAŞMAKÇI",
    "MAHALLE": "ÇAĞLAYAN",
    "id": 1087
  },
  {
    "İL": "AFYONKARAHİSAR",
    "İLÇE": "BAŞMAKÇI",
    "MAHALLE": "MİMAR SİNAN",
    "id": 1088
  },
  {
    "İL": "AFYONKARAHİSAR",
    "İLÇE": "BAŞMAKÇI",
    "MAHALLE": "YENİ",
    "id": 1089
  },
  {
    "İL": "AFYONKARAHİSAR",
    "İLÇE": "BAŞMAKÇI",
    "MAHALLE": "YUKARI HİLAL",
    "id": 1090
  },
  {
    "İL": "AFYONKARAHİSAR",
    "İLÇE": "BAŞMAKÇI",
    "MAHALLE": "FATİH",
    "id": 1091
  },
  {
    "İL": "AFYONKARAHİSAR",
    "İLÇE": "BAŞMAKÇI",
    "MAHALLE": "GÜLİSTAN",
    "id": 1092
  },
  {
    "İL": "AFYONKARAHİSAR",
    "İLÇE": "SANDIKLI",
    "MAHALLE": "AKHARIM, DİKMEN",
    "id": 1093
  },
  {
    "İL": "AFYONKARAHİSAR",
    "İLÇE": "SANDIKLI",
    "MAHALLE": "HİSAR",
    "id": 1094
  },
  {
    "İL": "AFYONKARAHİSAR",
    "İLÇE": "SANDIKLI",
    "MAHALLE": "SAZAK",
    "id": 1095
  },
  {
    "İL": "AFYONKARAHİSAR",
    "İLÇE": "SANDIKLI",
    "MAHALLE": "YUNUS EMRE",
    "id": 1096
  },
  {
    "İL": "AFYONKARAHİSAR",
    "İLÇE": "SANDIKLI",
    "MAHALLE": "ÇAY",
    "id": 1097
  },
  {
    "İL": "AFYONKARAHİSAR",
    "İLÇE": "SANDIKLI",
    "MAHALLE": "SANDIKLI OSB",
    "id": 1098
  },
  {
    "İL": "AFYONKARAHİSAR",
    "İLÇE": "SANDIKLI",
    "MAHALLE": "AKHARIM, ÇİĞİLTEPE",
    "id": 1099
  },
  {
    "İL": "AFYONKARAHİSAR",
    "İLÇE": "SANDIKLI",
    "MAHALLE": "ÇAKIR",
    "id": 1100
  },
  {
    "İL": "AFYONKARAHİSAR",
    "İLÇE": "SANDIKLI",
    "MAHALLE": "ECE",
    "id": 1101
  },
  {
    "İL": "AFYONKARAHİSAR",
    "İLÇE": "SANDIKLI",
    "MAHALLE": "CUMA",
    "id": 1102
  },
  {
    "İL": "AFYONKARAHİSAR",
    "İLÇE": "SANDIKLI",
    "MAHALLE": "KEVSER",
    "id": 1103
  },
  {
    "İL": "AFYONKARAHİSAR",
    "İLÇE": "SANDIKLI",
    "MAHALLE": "TAPDUK EMRE",
    "id": 1104
  },
  {
    "İL": "AFYONKARAHİSAR",
    "İLÇE": "SANDIKLI",
    "MAHALLE": "ZAFER",
    "id": 1105
  },
  {
    "İL": "AFYONKARAHİSAR",
    "İLÇE": "SANDIKLI",
    "MAHALLE": "AKHARIM, HİSAR",
    "id": 1106
  },
  {
    "İL": "AFYONKARAHİSAR",
    "İLÇE": "SANDIKLI",
    "MAHALLE": "İSTASYON",
    "id": 1107
  },
  {
    "İL": "AFYONKARAHİSAR",
    "İLÇE": "SANDIKLI",
    "MAHALLE": "ŞİRİNEVLER",
    "id": 1108
  },
  {
    "İL": "AFYONKARAHİSAR",
    "İLÇE": "SANDIKLI",
    "MAHALLE": "FATİH",
    "id": 1109
  },
  {
    "İL": "AFYONKARAHİSAR",
    "İLÇE": "İHSANİYE",
    "MAHALLE": "DÖĞER, KERVANSARAY",
    "id": 1110
  },
  {
    "İL": "AFYONKARAHİSAR",
    "İLÇE": "İHSANİYE",
    "MAHALLE": "HÜRRİYET",
    "id": 1111
  },
  {
    "İL": "AFYONKARAHİSAR",
    "İLÇE": "İHSANİYE",
    "MAHALLE": "SUSUZ, OSMANİYE",
    "id": 1112
  },
  {
    "İL": "AFYONKARAHİSAR",
    "İLÇE": "İHSANİYE",
    "MAHALLE": "ZAFER",
    "id": 1113
  },
  {
    "İL": "AFYONKARAHİSAR",
    "İLÇE": "İHSANİYE",
    "MAHALLE": "DÖĞER, YUNUS EMRE",
    "id": 1114
  },
  {
    "İL": "AFYONKARAHİSAR",
    "İLÇE": "İHSANİYE",
    "MAHALLE": "YAYLABAĞI, BAHÇELİEVLER",
    "id": 1115
  },
  {
    "İL": "AFYONKARAHİSAR",
    "İLÇE": "İHSANİYE",
    "MAHALLE": "YAYLABAĞI, ATATÜRK",
    "id": 1116
  },
  {
    "İL": "AFYONKARAHİSAR",
    "İLÇE": "İHSANİYE",
    "MAHALLE": "DÖĞER, YENİ",
    "id": 1117
  },
  {
    "İL": "AFYONKARAHİSAR",
    "İLÇE": "İHSANİYE",
    "MAHALLE": "KAYIHAN, TÜRBE",
    "id": 1118
  },
  {
    "İL": "AFYONKARAHİSAR",
    "İLÇE": "İHSANİYE",
    "MAHALLE": "CUMHURİYET",
    "id": 1119
  },
  {
    "İL": "AFYONKARAHİSAR",
    "İLÇE": "İHSANİYE",
    "MAHALLE": "YENİKENT",
    "id": 1120
  },
  {
    "İL": "AFYONKARAHİSAR",
    "İLÇE": "İHSANİYE",
    "MAHALLE": "FATİH",
    "id": 1121
  },
  {
    "İL": "AFYONKARAHİSAR",
    "İLÇE": "İHSANİYE",
    "MAHALLE": "GAZLIGÖL, YUNUS EMRE",
    "id": 1122
  },
  {
    "İL": "AFYONKARAHİSAR",
    "İLÇE": "İHSANİYE",
    "MAHALLE": "DÖĞER, FATİH",
    "id": 1123
  },
  {
    "İL": "AFYONKARAHİSAR",
    "İLÇE": "İHSANİYE",
    "MAHALLE": "GAZLIGÖL, FATİH",
    "id": 1124
  },
  {
    "İL": "AFYONKARAHİSAR",
    "İLÇE": "İHSANİYE",
    "MAHALLE": "YAYLABAĞI, ESENTEPE",
    "id": 1125
  },
  {
    "İL": "AFYONKARAHİSAR",
    "İLÇE": "İHSANİYE",
    "MAHALLE": "KAYIHAN, CUMHURİYET",
    "id": 1126
  },
  {
    "İL": "AFYONKARAHİSAR",
    "İLÇE": "İHSANİYE",
    "MAHALLE": "ŞAHİNLER",
    "id": 1127
  },
  {
    "İL": "AFYONKARAHİSAR",
    "İLÇE": "İHSANİYE",
    "MAHALLE": "GAZLIGÖL, BELCE",
    "id": 1128
  },
  {
    "İL": "AFYONKARAHİSAR",
    "İLÇE": "İHSANİYE",
    "MAHALLE": "KAYIHAN, PINAR",
    "id": 1129
  },
  {
    "İL": "AFYONKARAHİSAR",
    "İLÇE": "İHSANİYE",
    "MAHALLE": "AKÖREN",
    "id": 1130
  },
  {
    "İL": "AFYONKARAHİSAR",
    "İLÇE": "İHSANİYE",
    "MAHALLE": "GAZLIGÖL, CUMHURİYET",
    "id": 1131
  },
  {
    "İL": "AFYONKARAHİSAR",
    "İLÇE": "İHSANİYE",
    "MAHALLE": "KAYIHAN, KUNDUZLU",
    "id": 1132
  },
  {
    "İL": "AFYONKARAHİSAR",
    "İLÇE": "İSCEHİSAR",
    "MAHALLE": "KURTULUŞ",
    "id": 1133
  },
  {
    "İL": "AFYONKARAHİSAR",
    "İLÇE": "İSCEHİSAR",
    "MAHALLE": "ESKİ HAMAM",
    "id": 1134
  },
  {
    "İL": "AFYONKARAHİSAR",
    "İLÇE": "İSCEHİSAR",
    "MAHALLE": "ÇUKUR",
    "id": 1135
  },
  {
    "İL": "AFYONKARAHİSAR",
    "İLÇE": "İSCEHİSAR",
    "MAHALLE": "SEYDİLER, HASAN BASRİ",
    "id": 1136
  },
  {
    "İL": "AFYONKARAHİSAR",
    "İLÇE": "İSCEHİSAR",
    "MAHALLE": "SELÇUKLU",
    "id": 1137
  },
  {
    "İL": "AFYONKARAHİSAR",
    "İLÇE": "İSCEHİSAR",
    "MAHALLE": "ESENTEPE",
    "id": 1138
  },
  {
    "İL": "AFYONKARAHİSAR",
    "İLÇE": "İSCEHİSAR",
    "MAHALLE": "MERMER OSB",
    "id": 1139
  },
  {
    "İL": "AFYONKARAHİSAR",
    "İLÇE": "İSCEHİSAR",
    "MAHALLE": "SEYDİLER, CUMHURİYET",
    "id": 1140
  },
  {
    "İL": "AFYONKARAHİSAR",
    "İLÇE": "İSCEHİSAR",
    "MAHALLE": "TEPECİK",
    "id": 1141
  },
  {
    "İL": "AFYONKARAHİSAR",
    "İLÇE": "İSCEHİSAR",
    "MAHALLE": "FATİH",
    "id": 1142
  },
  {
    "İL": "AFYONKARAHİSAR",
    "İLÇE": "İSCEHİSAR",
    "MAHALLE": "ZEYBEK",
    "id": 1143
  },
  {
    "İL": "AFYONKARAHİSAR",
    "İLÇE": "İSCEHİSAR",
    "MAHALLE": "ŞİRİNEVLER",
    "id": 1144
  },
  {
    "İL": "AFYONKARAHİSAR",
    "İLÇE": "İSCEHİSAR",
    "MAHALLE": "KAVAK",
    "id": 1145
  },
  {
    "İL": "AFYONKARAHİSAR",
    "İLÇE": "İSCEHİSAR",
    "MAHALLE": "MEDRESE",
    "id": 1146
  },
  {
    "İL": "AFYONKARAHİSAR",
    "İLÇE": "İSCEHİSAR",
    "MAHALLE": "CUMHURİYET",
    "id": 1147
  },
  {
    "İL": "AFYONKARAHİSAR",
    "İLÇE": "ŞUHUT",
    "MAHALLE": "ALTIGÖZ",
    "id": 1148
  },
  {
    "İL": "AFYONKARAHİSAR",
    "İLÇE": "ŞUHUT",
    "MAHALLE": "ZAFER",
    "id": 1149
  },
  {
    "İL": "AFYONKARAHİSAR",
    "İLÇE": "ŞUHUT",
    "MAHALLE": "İPLİK",
    "id": 1150
  },
  {
    "İL": "AFYONKARAHİSAR",
    "İLÇE": "ŞUHUT",
    "MAHALLE": "KARAADİLLİ, DEVELİ",
    "id": 1151
  },
  {
    "İL": "AFYONKARAHİSAR",
    "İLÇE": "ŞUHUT",
    "MAHALLE": "KARAADİLLİ, ERENLER",
    "id": 1152
  },
  {
    "İL": "AFYONKARAHİSAR",
    "İLÇE": "ŞUHUT",
    "MAHALLE": "BAŞ",
    "id": 1153
  },
  {
    "İL": "AFYONKARAHİSAR",
    "İLÇE": "ŞUHUT",
    "MAHALLE": "HACI MUSA",
    "id": 1154
  },
  {
    "İL": "AFYONKARAHİSAR",
    "İLÇE": "ŞUHUT",
    "MAHALLE": "PAZAR",
    "id": 1155
  },
  {
    "İL": "AFYONKARAHİSAR",
    "İLÇE": "ŞUHUT",
    "MAHALLE": "GAZİPAŞA",
    "id": 1156
  },
  {
    "İL": "AFYONKARAHİSAR",
    "İLÇE": "ŞUHUT",
    "MAHALLE": "İSTİKLAL",
    "id": 1157
  },
  {
    "İL": "AFYONKARAHİSAR",
    "İLÇE": "ŞUHUT",
    "MAHALLE": "MEHMET AKİF ERSOY",
    "id": 1158
  },
  {
    "İL": "AFYONKARAHİSAR",
    "İLÇE": "ŞUHUT",
    "MAHALLE": "HİSAR",
    "id": 1159
  },
  {
    "İL": "AFYONKARAHİSAR",
    "İLÇE": "ŞUHUT",
    "MAHALLE": "KARAADİLLİ, ÇAĞLAYAN",
    "id": 1160
  },
  {
    "İL": "AFYONKARAHİSAR",
    "İLÇE": "ŞUHUT",
    "MAHALLE": "TAŞLICA",
    "id": 1161
  },
  {
    "İL": "AFYONKARAHİSAR",
    "İLÇE": "ŞUHUT",
    "MAHALLE": "YALI",
    "id": 1162
  },
  {
    "İL": "AFYONKARAHİSAR",
    "İLÇE": "ŞUHUT",
    "MAHALLE": "KARAADİLLİ, ZAFER",
    "id": 1163
  },
  {
    "İL": "AFYONKARAHİSAR",
    "İLÇE": "ŞUHUT",
    "MAHALLE": "KURTULUŞ",
    "id": 1164
  },
  {
    "İL": "AFYONKARAHİSAR",
    "İLÇE": "BOLVADİN",
    "MAHALLE": "BAĞLARBAŞI",
    "id": 1165
  },
  {
    "İL": "AFYONKARAHİSAR",
    "İLÇE": "BOLVADİN",
    "MAHALLE": "ERKMEN",
    "id": 1166
  },
  {
    "İL": "AFYONKARAHİSAR",
    "İLÇE": "BOLVADİN",
    "MAHALLE": "HACI HALİFE",
    "id": 1167
  },
  {
    "İL": "AFYONKARAHİSAR",
    "İLÇE": "BOLVADİN",
    "MAHALLE": "MÜSLÜMANA",
    "id": 1168
  },
  {
    "İL": "AFYONKARAHİSAR",
    "İLÇE": "BOLVADİN",
    "MAHALLE": "ÖZBURUN, ULUCAMİ",
    "id": 1169
  },
  {
    "İL": "AFYONKARAHİSAR",
    "İLÇE": "BOLVADİN",
    "MAHALLE": "KARABAĞLAR",
    "id": 1170
  },
  {
    "İL": "AFYONKARAHİSAR",
    "İLÇE": "BOLVADİN",
    "MAHALLE": "LALA SİNAN PAŞA",
    "id": 1171
  },
  {
    "İL": "AFYONKARAHİSAR",
    "İLÇE": "BOLVADİN",
    "MAHALLE": "SELÇUKLU",
    "id": 1172
  },
  {
    "İL": "AFYONKARAHİSAR",
    "İLÇE": "BOLVADİN",
    "MAHALLE": "YENİ",
    "id": 1173
  },
  {
    "İL": "AFYONKARAHİSAR",
    "İLÇE": "BOLVADİN",
    "MAHALLE": "YUKARI GÖKÇEYAYLA",
    "id": 1174
  },
  {
    "İL": "AFYONKARAHİSAR",
    "İLÇE": "BOLVADİN",
    "MAHALLE": "HACI ESAT",
    "id": 1175
  },
  {
    "İL": "AFYONKARAHİSAR",
    "İLÇE": "BOLVADİN",
    "MAHALLE": "HACI YUSUF",
    "id": 1176
  },
  {
    "İL": "AFYONKARAHİSAR",
    "İLÇE": "BOLVADİN",
    "MAHALLE": "CİRİT",
    "id": 1177
  },
  {
    "İL": "AFYONKARAHİSAR",
    "İLÇE": "BOLVADİN",
    "MAHALLE": "DİŞLİ, ŞEYH ŞAMİL",
    "id": 1178
  },
  {
    "İL": "AFYONKARAHİSAR",
    "İLÇE": "BOLVADİN",
    "MAHALLE": "DİŞLİ, YUKARI",
    "id": 1179
  },
  {
    "İL": "AFYONKARAHİSAR",
    "İLÇE": "BOLVADİN",
    "MAHALLE": "EMRULLAH",
    "id": 1180
  },
  {
    "İL": "AFYONKARAHİSAR",
    "İLÇE": "BOLVADİN",
    "MAHALLE": "ÖZBURUN, ÇAYBAŞI",
    "id": 1181
  },
  {
    "İL": "AFYONKARAHİSAR",
    "İLÇE": "BOLVADİN",
    "MAHALLE": "BUCAK",
    "id": 1182
  },
  {
    "İL": "AFYONKARAHİSAR",
    "İLÇE": "BOLVADİN",
    "MAHALLE": "DİŞLİ, KÖPRÜBAŞI",
    "id": 1183
  },
  {
    "İL": "AFYONKARAHİSAR",
    "İLÇE": "BOLVADİN",
    "MAHALLE": "DİŞLİ, YAVUZ SELİM",
    "id": 1184
  },
  {
    "İL": "AFYONKARAHİSAR",
    "İLÇE": "BOLVADİN",
    "MAHALLE": "YENİ DOĞAN",
    "id": 1185
  },
  {
    "İL": "AFYONKARAHİSAR",
    "İLÇE": "BOLVADİN",
    "MAHALLE": "BOLVADİN OSB",
    "id": 1186
  },
  {
    "İL": "AFYONKARAHİSAR",
    "İLÇE": "BOLVADİN",
    "MAHALLE": "ÖMEROĞLU",
    "id": 1187
  },
  {
    "İL": "AFYONKARAHİSAR",
    "İLÇE": "BOLVADİN",
    "MAHALLE": "ŞAZİ",
    "id": 1188
  },
  {
    "İL": "AFYONKARAHİSAR",
    "İLÇE": "BOLVADİN",
    "MAHALLE": "ALİ EFENDİ",
    "id": 1189
  },
  {
    "İL": "AFYONKARAHİSAR",
    "İLÇE": "BOLVADİN",
    "MAHALLE": "HASTANE",
    "id": 1190
  },
  {
    "İL": "AFYONKARAHİSAR",
    "İLÇE": "BOLVADİN",
    "MAHALLE": "MESCİT",
    "id": 1191
  },
  {
    "İL": "AFYONKARAHİSAR",
    "İLÇE": "BOLVADİN",
    "MAHALLE": "AKÇEŞME",
    "id": 1192
  },
  {
    "İL": "AFYONKARAHİSAR",
    "İLÇE": "BOLVADİN",
    "MAHALLE": "DİŞLİ, ÇAYBAŞI",
    "id": 1193
  },
  {
    "İL": "AFYONKARAHİSAR",
    "İLÇE": "BOLVADİN",
    "MAHALLE": "DİŞLİ, MEVLANA",
    "id": 1194
  },
  {
    "İL": "AFYONKARAHİSAR",
    "İLÇE": "BOLVADİN",
    "MAHALLE": "AŞAĞI, GÖKÇEYAYLA",
    "id": 1195
  },
  {
    "İL": "AFYONKARAHİSAR",
    "İLÇE": "BOLVADİN",
    "MAHALLE": "AYDINLAR",
    "id": 1196
  },
  {
    "İL": "AFYONKARAHİSAR",
    "İLÇE": "BOLVADİN",
    "MAHALLE": "FATİH",
    "id": 1197
  },
  {
    "İL": "AFYONKARAHİSAR",
    "İLÇE": "BOLVADİN",
    "MAHALLE": "HİSAR",
    "id": 1198
  },
  {
    "İL": "AFYONKARAHİSAR",
    "İLÇE": "BOLVADİN",
    "MAHALLE": "KIRKGÖZ",
    "id": 1199
  },
  {
    "İL": "AFYONKARAHİSAR",
    "İLÇE": "BOLVADİN",
    "MAHALLE": "ALACA",
    "id": 1200
  },
  {
    "İL": "AFYONKARAHİSAR",
    "İLÇE": "BOLVADİN",
    "MAHALLE": "BADEMLİ",
    "id": 1201
  },
  {
    "İL": "AFYONKARAHİSAR",
    "İLÇE": "BOLVADİN",
    "MAHALLE": "BAĞLARÜSTÜ",
    "id": 1202
  },
  {
    "İL": "AFYONKARAHİSAR",
    "İLÇE": "BOLVADİN",
    "MAHALLE": "ÇARDAKLI",
    "id": 1203
  },
  {
    "İL": "AFYONKARAHİSAR",
    "İLÇE": "BOLVADİN",
    "MAHALLE": "DİŞLİ, MALAZGİRT",
    "id": 1204
  },
  {
    "İL": "AFYONKARAHİSAR",
    "İLÇE": "BOLVADİN",
    "MAHALLE": "KAYMAZ",
    "id": 1205
  },
  {
    "İL": "AFYONKARAHİSAR",
    "İLÇE": "BOLVADİN",
    "MAHALLE": "KESTEMET",
    "id": 1206
  },
  {
    "İL": "AFYONKARAHİSAR",
    "İLÇE": "BOLVADİN",
    "MAHALLE": "KONAK",
    "id": 1207
  },
  {
    "İL": "AFYONKARAHİSAR",
    "İLÇE": "BOLVADİN",
    "MAHALLE": "ÖZBURUN, BAHÇELİEVLER",
    "id": 1208
  },
  {
    "İL": "AFYONKARAHİSAR",
    "İLÇE": "BOLVADİN",
    "MAHALLE": "ÖZBURUN, ÜSKÜDAR",
    "id": 1209
  },
  {
    "İL": "AFYONKARAHİSAR",
    "İLÇE": "BOLVADİN",
    "MAHALLE": "ETHEM KELEKÇİ",
    "id": 1210
  },
  {
    "İL": "AFYONKARAHİSAR",
    "İLÇE": "BOLVADİN",
    "MAHALLE": "HACI ÖMER",
    "id": 1211
  },
  {
    "İL": "AFYONKARAHİSAR",
    "İLÇE": "BOLVADİN",
    "MAHALLE": "İHSANİYE",
    "id": 1212
  },
  {
    "İL": "AFYONKARAHİSAR",
    "İLÇE": "BOLVADİN",
    "MAHALLE": "KALE",
    "id": 1213
  },
  {
    "İL": "AFYONKARAHİSAR",
    "İLÇE": "BOLVADİN",
    "MAHALLE": "YAKUP ŞEVKİ PAŞA",
    "id": 1214
  },
  {
    "İL": "AFYONKARAHİSAR",
    "İLÇE": "BOLVADİN",
    "MAHALLE": "DİŞLİ YUNUS EMRE",
    "id": 1215
  },
  {
    "İL": "AFYONKARAHİSAR",
    "İLÇE": "BOLVADİN",
    "MAHALLE": "İMARET",
    "id": 1216
  },
  {
    "İL": "AFYONKARAHİSAR",
    "İLÇE": "BOLVADİN",
    "MAHALLE": "ŞIHLAR",
    "id": 1217
  },
  {
    "İL": "AFYONKARAHİSAR",
    "İLÇE": "BOLVADİN",
    "MAHALLE": "BEKİR AĞA",
    "id": 1218
  },
  {
    "İL": "AFYONKARAHİSAR",
    "İLÇE": "BOLVADİN",
    "MAHALLE": "DİŞLİ, FATİH",
    "id": 1219
  },
  {
    "İL": "AFYONKARAHİSAR",
    "İLÇE": "BOLVADİN",
    "MAHALLE": "MALAZGİRT",
    "id": 1220
  },
  {
    "İL": "AFYONKARAHİSAR",
    "İLÇE": "BOLVADİN",
    "MAHALLE": "YENİCE",
    "id": 1221
  },
  {
    "İL": "AFYONKARAHİSAR",
    "İLÇE": "BOLVADİN",
    "MAHALLE": "BAHÇELİEVLER",
    "id": 1222
  },
  {
    "İL": "AFYONKARAHİSAR",
    "İLÇE": "BOLVADİN",
    "MAHALLE": "DİŞLİ, OKUL",
    "id": 1223
  },
  {
    "İL": "AFYONKARAHİSAR",
    "İLÇE": "BOLVADİN",
    "MAHALLE": "GÖLBAŞI",
    "id": 1224
  },
  {
    "İL": "AFYONKARAHİSAR",
    "İLÇE": "BOLVADİN",
    "MAHALLE": "SÜLEYMANİYE",
    "id": 1225
  },
  {
    "İL": "AFYONKARAHİSAR",
    "İLÇE": "BOLVADİN",
    "MAHALLE": "TAŞAĞIL",
    "id": 1226
  },
  {
    "İL": "AFYONKARAHİSAR",
    "İLÇE": "BOLVADİN",
    "MAHALLE": "KIRKLAR",
    "id": 1227
  },
  {
    "İL": "AFYONKARAHİSAR",
    "İLÇE": "BOLVADİN",
    "MAHALLE": "ÖZBURUN, ŞEHİRÖNÜ",
    "id": 1228
  },
  {
    "İL": "AFYONKARAHİSAR",
    "İLÇE": "BOLVADİN",
    "MAHALLE": "YILDIRIM",
    "id": 1229
  },
  {
    "İL": "AFYONKARAHİSAR",
    "İLÇE": "DİNAR",
    "MAHALLE": "BAĞLAR",
    "id": 1230
  },
  {
    "İL": "AFYONKARAHİSAR",
    "İLÇE": "DİNAR",
    "MAHALLE": "CAMİKEBİR",
    "id": 1231
  },
  {
    "İL": "AFYONKARAHİSAR",
    "İLÇE": "DİNAR",
    "MAHALLE": "ALTMIŞEVLER",
    "id": 1232
  },
  {
    "İL": "AFYONKARAHİSAR",
    "İLÇE": "DİNAR",
    "MAHALLE": "CUMHURİYET",
    "id": 1233
  },
  {
    "İL": "AFYONKARAHİSAR",
    "İLÇE": "DİNAR",
    "MAHALLE": "ATATÜRK",
    "id": 1234
  },
  {
    "İL": "AFYONKARAHİSAR",
    "İLÇE": "DİNAR",
    "MAHALLE": "DÖRTYOL",
    "id": 1235
  },
  {
    "İL": "AFYONKARAHİSAR",
    "İLÇE": "DİNAR",
    "MAHALLE": "ILICA",
    "id": 1236
  },
  {
    "İL": "AFYONKARAHİSAR",
    "İLÇE": "DİNAR",
    "MAHALLE": "İTFAİYE",
    "id": 1237
  },
  {
    "İL": "AFYONKARAHİSAR",
    "İLÇE": "DİNAR",
    "MAHALLE": "HAYDARLI, CUMHURİYET",
    "id": 1238
  },
  {
    "İL": "AFYONKARAHİSAR",
    "İLÇE": "DİNAR",
    "MAHALLE": "HAYDARLI, ÖRNEK",
    "id": 1239
  },
  {
    "İL": "AFYONKARAHİSAR",
    "İLÇE": "DİNAR",
    "MAHALLE": "SANTRAL",
    "id": 1240
  },
  {
    "İL": "AFYONKARAHİSAR",
    "İLÇE": "DİNAR",
    "MAHALLE": "TATARLI, YEŞİLYURT",
    "id": 1241
  },
  {
    "İL": "AFYONKARAHİSAR",
    "İLÇE": "DİNAR",
    "MAHALLE": "EMNİYET",
    "id": 1242
  },
  {
    "İL": "AFYONKARAHİSAR",
    "İLÇE": "DİNAR",
    "MAHALLE": "GAZİ MEHMET ÇAVUŞ",
    "id": 1243
  },
  {
    "İL": "AFYONKARAHİSAR",
    "İLÇE": "DİNAR",
    "MAHALLE": "TATARLI, FATİH",
    "id": 1244
  },
  {
    "İL": "AFYONKARAHİSAR",
    "İLÇE": "DİNAR",
    "MAHALLE": "HAYDARLI, OCAKLI",
    "id": 1245
  },
  {
    "İL": "AFYONKARAHİSAR",
    "İLÇE": "DİNAR",
    "MAHALLE": "OTOGAR",
    "id": 1246
  },
  {
    "İL": "AFYONKARAHİSAR",
    "İLÇE": "DİNAR",
    "MAHALLE": "SUÇIKAN",
    "id": 1247
  },
  {
    "İL": "AFYONKARAHİSAR",
    "İLÇE": "DİNAR",
    "MAHALLE": "HAYDARLI, İSTİKLAL",
    "id": 1248
  },
  {
    "İL": "AFYONKARAHİSAR",
    "İLÇE": "DİNAR",
    "MAHALLE": "TATARLI, ALTINHİSAR",
    "id": 1249
  },
  {
    "İL": "AFYONKARAHİSAR",
    "İLÇE": "DİNAR",
    "MAHALLE": "HAYDARLI, YENİ",
    "id": 1250
  },
  {
    "İL": "AFYONKARAHİSAR",
    "İLÇE": "DİNAR",
    "MAHALLE": "TATARLI, CUMHURİYET",
    "id": 1251
  },
  {
    "İL": "AFYONKARAHİSAR",
    "İLÇE": "DİNAR",
    "MAHALLE": "HÜRRİYET",
    "id": 1252
  },
  {
    "İL": "AFYONKARAHİSAR",
    "İLÇE": "DİNAR",
    "MAHALLE": "İNCİRLİ",
    "id": 1253
  },
  {
    "İL": "AFYONKARAHİSAR",
    "İLÇE": "DİNAR",
    "MAHALLE": "İSTASYON",
    "id": 1254
  },
  {
    "İL": "AFYONKARAHİSAR",
    "İLÇE": "DİNAR",
    "MAHALLE": "TOPTEPE",
    "id": 1255
  },
  {
    "İL": "AFYONKARAHİSAR",
    "İLÇE": "DİNAR",
    "MAHALLE": "ADLİYE",
    "id": 1256
  },
  {
    "İL": "AFYONKARAHİSAR",
    "İLÇE": "DİNAR",
    "MAHALLE": "SANAYİ",
    "id": 1257
  },
  {
    "İL": "AFYONKARAHİSAR",
    "İLÇE": "DİNAR",
    "MAHALLE": "TATARLI, ÇAMLICA",
    "id": 1258
  },
  {
    "İL": "AFYONKARAHİSAR",
    "İLÇE": "DİNAR",
    "MAHALLE": "HAYDARLI, MERKEZ",
    "id": 1259
  },
  {
    "İL": "AFYONKARAHİSAR",
    "İLÇE": "DİNAR",
    "MAHALLE": "KONAK",
    "id": 1260
  },
  {
    "İL": "AFYONKARAHİSAR",
    "İLÇE": "DİNAR",
    "MAHALLE": "PINARBAŞI",
    "id": 1261
  },
  {
    "İL": "AFYONKARAHİSAR",
    "İLÇE": "DİNAR",
    "MAHALLE": "STADYUM",
    "id": 1262
  },
  {
    "İL": "AFYONKARAHİSAR",
    "İLÇE": "DİNAR",
    "MAHALLE": "PANCAR",
    "id": 1263
  },
  {
    "İL": "AFYONKARAHİSAR",
    "İLÇE": "DİNAR",
    "MAHALLE": "KORUBAŞI",
    "id": 1264
  },
  {
    "İL": "AFYONKARAHİSAR",
    "İLÇE": "DİNAR",
    "MAHALLE": "PAZAR",
    "id": 1265
  },
  {
    "İL": "AFYONKARAHİSAR",
    "İLÇE": "DİNAR",
    "MAHALLE": "ÜÇLERCE",
    "id": 1266
  },
  {
    "İL": "AFYONKARAHİSAR",
    "İLÇE": "DİNAR",
    "MAHALLE": "HAYDARLI, HÜRRİYET",
    "id": 1267
  },
  {
    "İL": "AFYONKARAHİSAR",
    "İLÇE": "DİNAR",
    "MAHALLE": "YENİ",
    "id": 1268
  },
  {
    "İL": "AFYONKARAHİSAR",
    "İLÇE": "DİNAR",
    "MAHALLE": "FATİH",
    "id": 1269
  },
  {
    "İL": "AFYONKARAHİSAR",
    "İLÇE": "DİNAR",
    "MAHALLE": "TATARLI, ÇAĞLAYAN",
    "id": 1270
  },
  {
    "İL": "AFYONKARAHİSAR",
    "İLÇE": "MERKEZ",
    "MAHALLE": "BEYYAZI, ATATÜRK",
    "id": 1271
  },
  {
    "İL": "AFYONKARAHİSAR",
    "İLÇE": "MERKEZ",
    "MAHALLE": "ÇAYIRBAĞ, UĞUR",
    "id": 1272
  },
  {
    "İL": "AFYONKARAHİSAR",
    "İLÇE": "MERKEZ",
    "MAHALLE": "GEBECELER, İSTİKLAL",
    "id": 1273
  },
  {
    "İL": "AFYONKARAHİSAR",
    "İLÇE": "MERKEZ",
    "MAHALLE": "IŞIKLAR, CUMHURİYET",
    "id": 1274
  },
  {
    "İL": "AFYONKARAHİSAR",
    "İLÇE": "MERKEZ",
    "MAHALLE": "KANLICA",
    "id": 1275
  },
  {
    "İL": "AFYONKARAHİSAR",
    "İLÇE": "MERKEZ",
    "MAHALLE": "NURİBEY MAREŞAL FEVZİ ÇAKMAK",
    "id": 1276
  },
  {
    "İL": "AFYONKARAHİSAR",
    "İLÇE": "MERKEZ",
    "MAHALLE": "SALAR, YAVUZ SELİM",
    "id": 1277
  },
  {
    "İL": "AFYONKARAHİSAR",
    "İLÇE": "MERKEZ",
    "MAHALLE": "SÜLÜMENLİ, ŞEKER",
    "id": 1278
  },
  {
    "İL": "AFYONKARAHİSAR",
    "İLÇE": "MERKEZ",
    "MAHALLE": "YARENLER",
    "id": 1279
  },
  {
    "İL": "AFYONKARAHİSAR",
    "İLÇE": "MERKEZ",
    "MAHALLE": "BEYYAZI, CUMHURİYET",
    "id": 1280
  },
  {
    "İL": "AFYONKARAHİSAR",
    "İLÇE": "MERKEZ",
    "MAHALLE": "DAİRECEP",
    "id": 1281
  },
  {
    "İL": "AFYONKARAHİSAR",
    "İLÇE": "MERKEZ",
    "MAHALLE": "DERVİŞPAŞA",
    "id": 1282
  },
  {
    "İL": "AFYONKARAHİSAR",
    "İLÇE": "MERKEZ",
    "MAHALLE": "KIŞLACIK",
    "id": 1283
  },
  {
    "İL": "AFYONKARAHİSAR",
    "İLÇE": "MERKEZ",
    "MAHALLE": "ÇAYIRBAĞ, ALİ ÇETİNAYA",
    "id": 1284
  },
  {
    "İL": "AFYONKARAHİSAR",
    "İLÇE": "MERKEZ",
    "MAHALLE": "ÇAYIRBAĞ, FATİH",
    "id": 1285
  },
  {
    "İL": "AFYONKARAHİSAR",
    "İLÇE": "MERKEZ",
    "MAHALLE": "ÇAYIRBAĞ, HUZUR",
    "id": 1286
  },
  {
    "İL": "AFYONKARAHİSAR",
    "İLÇE": "MERKEZ",
    "MAHALLE": "DEĞİRMENAYVALI, ŞEHİT AHMET",
    "id": 1287
  },
  {
    "İL": "AFYONKARAHİSAR",
    "İLÇE": "MERKEZ",
    "MAHALLE": "ESENTEPE",
    "id": 1288
  },
  {
    "İL": "AFYONKARAHİSAR",
    "İLÇE": "MERKEZ",
    "MAHALLE": "IŞIKLAR, HÜRRİYET",
    "id": 1289
  },
  {
    "İL": "AFYONKARAHİSAR",
    "İLÇE": "MERKEZ",
    "MAHALLE": "KOCATEPE, KOCATEPE",
    "id": 1290
  },
  {
    "İL": "AFYONKARAHİSAR",
    "İLÇE": "MERKEZ",
    "MAHALLE": "BEYAZIT",
    "id": 1291
  },
  {
    "İL": "AFYONKARAHİSAR",
    "İLÇE": "MERKEZ",
    "MAHALLE": "ÇIKRIK, YUNUSLAR",
    "id": 1292
  },
  {
    "İL": "AFYONKARAHİSAR",
    "İLÇE": "MERKEZ",
    "MAHALLE": "MARULCU",
    "id": 1293
  },
  {
    "İL": "AFYONKARAHİSAR",
    "İLÇE": "MERKEZ",
    "MAHALLE": "ALİ İHSAN PAŞA",
    "id": 1294
  },
  {
    "İL": "AFYONKARAHİSAR",
    "İLÇE": "MERKEZ",
    "MAHALLE": "DEMİRÇEVRE",
    "id": 1295
  },
  {
    "İL": "AFYONKARAHİSAR",
    "İLÇE": "MERKEZ",
    "MAHALLE": "GEBECELER, FATİH",
    "id": 1296
  },
  {
    "İL": "AFYONKARAHİSAR",
    "İLÇE": "MERKEZ",
    "MAHALLE": "HATTAT KARAHİSAR",
    "id": 1297
  },
  {
    "İL": "AFYONKARAHİSAR",
    "İLÇE": "MERKEZ",
    "MAHALLE": "KOCATEPE, KURTULUŞ",
    "id": 1298
  },
  {
    "İL": "AFYONKARAHİSAR",
    "İLÇE": "MERKEZ",
    "MAHALLE": "SALAR, HALİL İBRAHİM SULTAN",
    "id": 1299
  },
  {
    "İL": "AFYONKARAHİSAR",
    "İLÇE": "MERKEZ",
    "MAHALLE": "SUSUZ, GÖKHAN",
    "id": 1300
  },
  {
    "İL": "AFYONKARAHİSAR",
    "İLÇE": "MERKEZ",
    "MAHALLE": "SÜLÜMENLİ, ALTINDAĞ",
    "id": 1301
  },
  {
    "İL": "AFYONKARAHİSAR",
    "İLÇE": "MERKEZ",
    "MAHALLE": "YEŞİLYURT",
    "id": 1302
  },
  {
    "İL": "AFYONKARAHİSAR",
    "İLÇE": "MERKEZ",
    "MAHALLE": "GEBECELER, KOCATEPE",
    "id": 1303
  },
  {
    "İL": "AFYONKARAHİSAR",
    "İLÇE": "MERKEZ",
    "MAHALLE": "NURİBEY, FATİH",
    "id": 1304
  },
  {
    "İL": "AFYONKARAHİSAR",
    "İLÇE": "MERKEZ",
    "MAHALLE": "ÖRNEKEVLER",
    "id": 1305
  },
  {
    "İL": "AFYONKARAHİSAR",
    "İLÇE": "MERKEZ",
    "MAHALLE": "ATAKÖY",
    "id": 1306
  },
  {
    "İL": "AFYONKARAHİSAR",
    "İLÇE": "MERKEZ",
    "MAHALLE": "BAYATCIK",
    "id": 1307
  },
  {
    "İL": "AFYONKARAHİSAR",
    "İLÇE": "MERKEZ",
    "MAHALLE": "ÇAKIR",
    "id": 1308
  },
  {
    "İL": "AFYONKARAHİSAR",
    "İLÇE": "MERKEZ",
    "MAHALLE": "GÜVENEVLER",
    "id": 1309
  },
  {
    "İL": "AFYONKARAHİSAR",
    "İLÇE": "MERKEZ",
    "MAHALLE": "IŞIKLAR, YENİ",
    "id": 1310
  },
  {
    "İL": "AFYONKARAHİSAR",
    "İLÇE": "MERKEZ",
    "MAHALLE": "KÜÇÜKÇOBANLI",
    "id": 1311
  },
  {
    "İL": "AFYONKARAHİSAR",
    "İLÇE": "MERKEZ",
    "MAHALLE": "OLUCAK",
    "id": 1312
  },
  {
    "İL": "AFYONKARAHİSAR",
    "İLÇE": "MERKEZ",
    "MAHALLE": "SALAR, GÜMÜŞ TEPE",
    "id": 1313
  },
  {
    "İL": "AFYONKARAHİSAR",
    "İLÇE": "MERKEZ",
    "MAHALLE": "AFYONKARAHİSAR OSB",
    "id": 1314
  },
  {
    "İL": "AFYONKARAHİSAR",
    "İLÇE": "MERKEZ",
    "MAHALLE": "CUMHURİYET",
    "id": 1315
  },
  {
    "İL": "AFYONKARAHİSAR",
    "İLÇE": "MERKEZ",
    "MAHALLE": "FAKIPAŞA",
    "id": 1316
  },
  {
    "İL": "AFYONKARAHİSAR",
    "İLÇE": "MERKEZ",
    "MAHALLE": "KOCATEPE",
    "id": 1317
  },
  {
    "İL": "AFYONKARAHİSAR",
    "İLÇE": "MERKEZ",
    "MAHALLE": "NAZMİ SAATÇİ",
    "id": 1318
  },
  {
    "İL": "AFYONKARAHİSAR",
    "İLÇE": "MERKEZ",
    "MAHALLE": "SALAR, FATİH",
    "id": 1319
  },
  {
    "İL": "AFYONKARAHİSAR",
    "İLÇE": "MERKEZ",
    "MAHALLE": "SUSUZ, SAKARYA",
    "id": 1320
  },
  {
    "İL": "AFYONKARAHİSAR",
    "İLÇE": "MERKEZ",
    "MAHALLE": "SÜLÜN, HİSAR",
    "id": 1321
  },
  {
    "İL": "AFYONKARAHİSAR",
    "İLÇE": "MERKEZ",
    "MAHALLE": "AKMESCİT",
    "id": 1322
  },
  {
    "İL": "AFYONKARAHİSAR",
    "İLÇE": "MERKEZ",
    "MAHALLE": "ALİ ÇETİNKAYA",
    "id": 1323
  },
  {
    "İL": "AFYONKARAHİSAR",
    "İLÇE": "MERKEZ",
    "MAHALLE": "GEBECELER, ZAFER",
    "id": 1324
  },
  {
    "İL": "AFYONKARAHİSAR",
    "İLÇE": "MERKEZ",
    "MAHALLE": "SAHİPATA",
    "id": 1325
  },
  {
    "İL": "AFYONKARAHİSAR",
    "İLÇE": "MERKEZ",
    "MAHALLE": "SÜMER",
    "id": 1326
  },
  {
    "İL": "AFYONKARAHİSAR",
    "İLÇE": "MERKEZ",
    "MAHALLE": "TACI AHMET",
    "id": 1327
  },
  {
    "İL": "AFYONKARAHİSAR",
    "İLÇE": "MERKEZ",
    "MAHALLE": "TAŞPINAR",
    "id": 1328
  },
  {
    "İL": "AFYONKARAHİSAR",
    "İLÇE": "MERKEZ",
    "MAHALLE": "ZAFER",
    "id": 1329
  },
  {
    "İL": "AFYONKARAHİSAR",
    "İLÇE": "MERKEZ",
    "MAHALLE": "BEYYAZI, ÖRNEK",
    "id": 1330
  },
  {
    "İL": "AFYONKARAHİSAR",
    "İLÇE": "MERKEZ",
    "MAHALLE": "FATİH",
    "id": 1331
  },
  {
    "İL": "AFYONKARAHİSAR",
    "İLÇE": "MERKEZ",
    "MAHALLE": "IŞIKLAR, YAKA",
    "id": 1332
  },
  {
    "İL": "AFYONKARAHİSAR",
    "İLÇE": "MERKEZ",
    "MAHALLE": "MECİDİYE",
    "id": 1333
  },
  {
    "İL": "AFYONKARAHİSAR",
    "İLÇE": "MERKEZ",
    "MAHALLE": "ORHANGAZİ",
    "id": 1334
  },
  {
    "İL": "AFYONKARAHİSAR",
    "İLÇE": "MERKEZ",
    "MAHALLE": "DÖRTYOL",
    "id": 1335
  },
  {
    "İL": "AFYONKARAHİSAR",
    "İLÇE": "MERKEZ",
    "MAHALLE": "EŞREFPAŞA",
    "id": 1336
  },
  {
    "İL": "AFYONKARAHİSAR",
    "İLÇE": "MERKEZ",
    "MAHALLE": "HAMİDİYE",
    "id": 1337
  },
  {
    "İL": "AFYONKARAHİSAR",
    "İLÇE": "MERKEZ",
    "MAHALLE": "KARŞIYAKA",
    "id": 1338
  },
  {
    "İL": "AFYONKARAHİSAR",
    "İLÇE": "MERKEZ",
    "MAHALLE": "KASIMPAŞA",
    "id": 1339
  },
  {
    "İL": "AFYONKARAHİSAR",
    "İLÇE": "MERKEZ",
    "MAHALLE": "KAYADİBİ",
    "id": 1340
  },
  {
    "İL": "AFYONKARAHİSAR",
    "İLÇE": "MERKEZ",
    "MAHALLE": "NURİBEY, MEHMET AKİF",
    "id": 1341
  },
  {
    "İL": "AFYONKARAHİSAR",
    "İLÇE": "MERKEZ",
    "MAHALLE": "OSMAN GAZİ",
    "id": 1342
  },
  {
    "İL": "AFYONKARAHİSAR",
    "İLÇE": "MERKEZ",
    "MAHALLE": "SUSUZ, SELÇUKLU",
    "id": 1343
  },
  {
    "İL": "AFYONKARAHİSAR",
    "İLÇE": "MERKEZ",
    "MAHALLE": "VEYSEL KARANİ",
    "id": 1344
  },
  {
    "İL": "AFYONKARAHİSAR",
    "İLÇE": "MERKEZ",
    "MAHALLE": "YENİCE",
    "id": 1345
  },
  {
    "İL": "AFYONKARAHİSAR",
    "İLÇE": "MERKEZ",
    "MAHALLE": "BATTALGAZİ",
    "id": 1346
  },
  {
    "İL": "AFYONKARAHİSAR",
    "İLÇE": "MERKEZ",
    "MAHALLE": "DUMLUPINAR",
    "id": 1347
  },
  {
    "İL": "AFYONKARAHİSAR",
    "İLÇE": "MERKEZ",
    "MAHALLE": "ERKMEN, HÜRRİYET",
    "id": 1348
  },
  {
    "İL": "AFYONKARAHİSAR",
    "İLÇE": "MERKEZ",
    "MAHALLE": "IŞIKLAR, İSTİKLAL",
    "id": 1349
  },
  {
    "İL": "AFYONKARAHİSAR",
    "İLÇE": "MERKEZ",
    "MAHALLE": "SUSUZ, OSMANLI",
    "id": 1350
  },
  {
    "İL": "AFYONKARAHİSAR",
    "İLÇE": "MERKEZ",
    "MAHALLE": "SÜLÜMENLİ, ZAFER",
    "id": 1351
  },
  {
    "İL": "AFYONKARAHİSAR",
    "İLÇE": "MERKEZ",
    "MAHALLE": "DEĞİRMENAYVALI, KURTULUŞ",
    "id": 1352
  },
  {
    "İL": "AFYONKARAHİSAR",
    "İLÇE": "MERKEZ",
    "MAHALLE": "ERENLER",
    "id": 1353
  },
  {
    "İL": "AFYONKARAHİSAR",
    "İLÇE": "MERKEZ",
    "MAHALLE": "ERTUĞRUL GAZİ",
    "id": 1354
  },
  {
    "İL": "AFYONKARAHİSAR",
    "İLÇE": "MERKEZ",
    "MAHALLE": "HOCA AHMET YESEVİ",
    "id": 1355
  },
  {
    "İL": "AFYONKARAHİSAR",
    "İLÇE": "MERKEZ",
    "MAHALLE": "IŞIKLAR, ATATÜRK",
    "id": 1356
  },
  {
    "İL": "AFYONKARAHİSAR",
    "İLÇE": "MERKEZ",
    "MAHALLE": "KARAMAN",
    "id": 1357
  },
  {
    "İL": "AFYONKARAHİSAR",
    "İLÇE": "MERKEZ",
    "MAHALLE": "SÜLÜMENLİ, ULUCAMİ",
    "id": 1358
  },
  {
    "İL": "AFYONKARAHİSAR",
    "İLÇE": "MERKEZ",
    "MAHALLE": "SÜLÜN, GÜLTEPE",
    "id": 1359
  },
  {
    "İL": "AFYONKARAHİSAR",
    "İLÇE": "MERKEZ",
    "MAHALLE": "AKÇİN",
    "id": 1360
  },
  {
    "İL": "AFYONKARAHİSAR",
    "İLÇE": "MERKEZ",
    "MAHALLE": "ÇIKRIK, ERENLER",
    "id": 1361
  },
  {
    "İL": "AFYONKARAHİSAR",
    "İLÇE": "MERKEZ",
    "MAHALLE": "ERKMEN, FEVZİ ÇAKMAK",
    "id": 1362
  },
  {
    "İL": "AFYONKARAHİSAR",
    "İLÇE": "MERKEZ",
    "MAHALLE": "MAREŞAL FEVZİ ÇAKMAK",
    "id": 1363
  },
  {
    "İL": "AFYONKARAHİSAR",
    "İLÇE": "MERKEZ",
    "MAHALLE": "SALAR, BARBAROS",
    "id": 1364
  },
  {
    "İL": "AFYONKARAHİSAR",
    "İLÇE": "MERKEZ",
    "MAHALLE": "SELÇUKLU",
    "id": 1365
  },
  {
    "İL": "AFYONKARAHİSAR",
    "İLÇE": "MERKEZ",
    "MAHALLE": "FETHİBEY, FATİH",
    "id": 1366
  },
  {
    "İL": "AFYONKARAHİSAR",
    "İLÇE": "MERKEZ",
    "MAHALLE": "FETHİBEY, YAVUZ SELİM",
    "id": 1367
  },
  {
    "İL": "AFYONKARAHİSAR",
    "İLÇE": "MERKEZ",
    "MAHALLE": "FETHİBEY, YUNUS EMRE",
    "id": 1368
  },
  {
    "İL": "AFYONKARAHİSAR",
    "İLÇE": "MERKEZ",
    "MAHALLE": "GEBECELER, YENİ",
    "id": 1369
  },
  {
    "İL": "AFYONKARAHİSAR",
    "İLÇE": "MERKEZ",
    "MAHALLE": "İSMAİL",
    "id": 1370
  },
  {
    "İL": "AFYONKARAHİSAR",
    "İLÇE": "MERKEZ",
    "MAHALLE": "NURİBEY, ALİ İHSAN PAŞA",
    "id": 1371
  },
  {
    "İL": "AFYONKARAHİSAR",
    "İLÇE": "MERKEZ",
    "MAHALLE": "SÜLÜMENLİ, CUMHURİYET",
    "id": 1372
  },
  {
    "İL": "AFYONKARAHİSAR",
    "İLÇE": "MERKEZ",
    "MAHALLE": "SÜLÜMENLİ, İSTİKLAL",
    "id": 1373
  },
  {
    "İL": "AFYONKARAHİSAR",
    "İLÇE": "MERKEZ",
    "MAHALLE": "BURMALI",
    "id": 1374
  },
  {
    "İL": "AFYONKARAHİSAR",
    "İLÇE": "MERKEZ",
    "MAHALLE": "ERKMEN, CUMHURİYET",
    "id": 1375
  },
  {
    "İL": "AFYONKARAHİSAR",
    "İLÇE": "MERKEZ",
    "MAHALLE": "GAZİ",
    "id": 1376
  },
  {
    "İL": "AFYONKARAHİSAR",
    "İLÇE": "MERKEZ",
    "MAHALLE": "HASAN KARAAĞAÇ",
    "id": 1377
  },
  {
    "İL": "AFYONKARAHİSAR",
    "İLÇE": "MERKEZ",
    "MAHALLE": "İSTİKLAL",
    "id": 1378
  },
  {
    "İL": "AFYONKARAHİSAR",
    "İLÇE": "MERKEZ",
    "MAHALLE": "SADIKBEY",
    "id": 1379
  },
  {
    "İL": "AFYONKARAHİSAR",
    "İLÇE": "MERKEZ",
    "MAHALLE": "YUNUS EMRE",
    "id": 1380
  },
  {
    "İL": "AFYONKARAHİSAR",
    "İLÇE": "EMİRDAĞ",
    "MAHALLE": "GÖMÜ, FATİH",
    "id": 1381
  },
  {
    "İL": "AFYONKARAHİSAR",
    "İLÇE": "EMİRDAĞ",
    "MAHALLE": "YENİ",
    "id": 1382
  },
  {
    "İL": "AFYONKARAHİSAR",
    "İLÇE": "EMİRDAĞ",
    "MAHALLE": "GÖMÜ, TOKİ",
    "id": 1383
  },
  {
    "İL": "AFYONKARAHİSAR",
    "İLÇE": "EMİRDAĞ",
    "MAHALLE": "KARŞIYAKA",
    "id": 1384
  },
  {
    "İL": "AFYONKARAHİSAR",
    "İLÇE": "EMİRDAĞ",
    "MAHALLE": "İNKİLAP",
    "id": 1385
  },
  {
    "İL": "AFYONKARAHİSAR",
    "İLÇE": "EMİRDAĞ",
    "MAHALLE": "ESKİ KACERLİ",
    "id": 1386
  },
  {
    "İL": "AFYONKARAHİSAR",
    "İLÇE": "EMİRDAĞ",
    "MAHALLE": "DAVULGA, ALASAKALLI",
    "id": 1387
  },
  {
    "İL": "AFYONKARAHİSAR",
    "İLÇE": "EMİRDAĞ",
    "MAHALLE": "DAVULGA, DOMURLU",
    "id": 1388
  },
  {
    "İL": "AFYONKARAHİSAR",
    "İLÇE": "EMİRDAĞ",
    "MAHALLE": "GÖMÜ, DÖRTYOL",
    "id": 1389
  },
  {
    "İL": "AFYONKARAHİSAR",
    "İLÇE": "EMİRDAĞ",
    "MAHALLE": "GÖMÜ, GÖKÇEYAKA",
    "id": 1390
  },
  {
    "İL": "AFYONKARAHİSAR",
    "İLÇE": "EMİRDAĞ",
    "MAHALLE": "DAVULGA, HİSARKÖY",
    "id": 1391
  },
  {
    "İL": "AFYONKARAHİSAR",
    "İLÇE": "EMİRDAĞ",
    "MAHALLE": "DAVULGA, KARAKUYU",
    "id": 1392
  },
  {
    "İL": "AFYONKARAHİSAR",
    "İLÇE": "EMİRDAĞ",
    "MAHALLE": "ÇİLLİ",
    "id": 1393
  },
  {
    "İL": "AFYONKARAHİSAR",
    "İLÇE": "EMİRDAĞ",
    "MAHALLE": "YENİDOĞAN",
    "id": 1394
  },
  {
    "İL": "AFYONKARAHİSAR",
    "İLÇE": "EMİRDAĞ",
    "MAHALLE": "DAVULGA, İNCİK",
    "id": 1395
  },
  {
    "İL": "AFYONKARAHİSAR",
    "İLÇE": "EMİRDAĞ",
    "MAHALLE": "MENDERES",
    "id": 1396
  },
  {
    "İL": "AFYONKARAHİSAR",
    "İLÇE": "EMİRDAĞ",
    "MAHALLE": "CUMHURİYET",
    "id": 1397
  },
  {
    "İL": "AFYONKARAHİSAR",
    "İLÇE": "EMİRDAĞ",
    "MAHALLE": "DAVULGA, SOFULU",
    "id": 1398
  },
  {
    "İL": "AFYONKARAHİSAR",
    "İLÇE": "EMİRDAĞ",
    "MAHALLE": "İNCİLİ",
    "id": 1399
  },
  {
    "İL": "AFYONKARAHİSAR",
    "İLÇE": "EMİRDAĞ",
    "MAHALLE": "GÖMÜ, BAĞLARBAŞI",
    "id": 1400
  },
  {
    "İL": "AFYONKARAHİSAR",
    "İLÇE": "EMİRDAĞ",
    "MAHALLE": "YENİ KACERLİ",
    "id": 1401
  },
  {
    "İL": "AFYONKARAHİSAR",
    "İLÇE": "SİNANPAŞA",
    "MAHALLE": "DÜZAĞAÇ, ZAFER",
    "id": 1402
  },
  {
    "İL": "AFYONKARAHİSAR",
    "İLÇE": "SİNANPAŞA",
    "MAHALLE": "AHMETPAŞA, ÇİĞİLTEPE",
    "id": 1403
  },
  {
    "İL": "AFYONKARAHİSAR",
    "İLÇE": "SİNANPAŞA",
    "MAHALLE": "AHMETPAŞA, DİBEKBAŞI",
    "id": 1404
  },
  {
    "İL": "AFYONKARAHİSAR",
    "İLÇE": "SİNANPAŞA",
    "MAHALLE": "ALİ ÇETİNKAYA",
    "id": 1405
  },
  {
    "İL": "AFYONKARAHİSAR",
    "İLÇE": "SİNANPAŞA",
    "MAHALLE": "KIRKA, ATATÜRK",
    "id": 1406
  },
  {
    "İL": "AFYONKARAHİSAR",
    "İLÇE": "SİNANPAŞA",
    "MAHALLE": "KÜÇÜKHÜYÜK, FATİH",
    "id": 1407
  },
  {
    "İL": "AFYONKARAHİSAR",
    "İLÇE": "SİNANPAŞA",
    "MAHALLE": "BAHÇELİEVLER",
    "id": 1408
  },
  {
    "İL": "AFYONKARAHİSAR",
    "İLÇE": "SİNANPAŞA",
    "MAHALLE": "TAŞOLUK, YENİ",
    "id": 1409
  },
  {
    "İL": "AFYONKARAHİSAR",
    "İLÇE": "SİNANPAŞA",
    "MAHALLE": "DÜZAĞAÇ, CUMHURİYET",
    "id": 1410
  },
  {
    "İL": "AFYONKARAHİSAR",
    "İLÇE": "SİNANPAŞA",
    "MAHALLE": "KILIÇARSLAN, FEVZİ ÇAKMAK",
    "id": 1411
  },
  {
    "İL": "AFYONKARAHİSAR",
    "İLÇE": "SİNANPAŞA",
    "MAHALLE": "AKÖREN, BAĞDAT",
    "id": 1412
  },
  {
    "İL": "AFYONKARAHİSAR",
    "İLÇE": "SİNANPAŞA",
    "MAHALLE": "KIRKA, YAVUZ SULTAN SELİM",
    "id": 1413
  },
  {
    "İL": "AFYONKARAHİSAR",
    "İLÇE": "SİNANPAŞA",
    "MAHALLE": "TAŞOLUK, ÇANKAYA",
    "id": 1414
  },
  {
    "İL": "AFYONKARAHİSAR",
    "İLÇE": "SİNANPAŞA",
    "MAHALLE": "KILIÇARSLAN, CUMHURİYET",
    "id": 1415
  },
  {
    "İL": "AFYONKARAHİSAR",
    "İLÇE": "SİNANPAŞA",
    "MAHALLE": "ÖĞRETMENLER",
    "id": 1416
  },
  {
    "İL": "AFYONKARAHİSAR",
    "İLÇE": "SİNANPAŞA",
    "MAHALLE": "AHMETPAŞA, HALKALI",
    "id": 1417
  },
  {
    "İL": "AFYONKARAHİSAR",
    "İLÇE": "SİNANPAŞA",
    "MAHALLE": "TINAZTEPE, YENİ",
    "id": 1418
  },
  {
    "İL": "AFYONKARAHİSAR",
    "İLÇE": "SİNANPAŞA",
    "MAHALLE": "AKÖREN, FATİH",
    "id": 1419
  },
  {
    "İL": "AFYONKARAHİSAR",
    "İLÇE": "SİNANPAŞA",
    "MAHALLE": "CUMHURİYET",
    "id": 1420
  },
  {
    "İL": "AFYONKARAHİSAR",
    "İLÇE": "SİNANPAŞA",
    "MAHALLE": "KÜÇÜKHÜYÜK, CUMHURİYET",
    "id": 1421
  },
  {
    "İL": "AFYONKARAHİSAR",
    "İLÇE": "SİNANPAŞA",
    "MAHALLE": "TINAZTEPE, SARAY",
    "id": 1422
  },
  {
    "İL": "AFYONKARAHİSAR",
    "İLÇE": "SİNANPAŞA",
    "MAHALLE": "KIRKA, YILDIRIM BEYAZIT",
    "id": 1423
  },
  {
    "İL": "AFYONKARAHİSAR",
    "İLÇE": "SİNANPAŞA",
    "MAHALLE": "KÜÇÜKHÜYÜK, ZAFER",
    "id": 1424
  },
  {
    "İL": "AFYONKARAHİSAR",
    "İLÇE": "SİNANPAŞA",
    "MAHALLE": "SERBAN, KÜMBET",
    "id": 1425
  },
  {
    "İL": "AFYONKARAHİSAR",
    "İLÇE": "SİNANPAŞA",
    "MAHALLE": "TAŞOLUK, CUMHURİYET",
    "id": 1426
  },
  {
    "İL": "AFYONKARAHİSAR",
    "İLÇE": "SİNANPAŞA",
    "MAHALLE": "TINAZTEPE, ZAFER",
    "id": 1427
  },
  {
    "İL": "AFYONKARAHİSAR",
    "İLÇE": "SİNANPAŞA",
    "MAHALLE": "AHMETPAŞA, KÜÇÜKTEPE",
    "id": 1428
  },
  {
    "İL": "AFYONKARAHİSAR",
    "İLÇE": "SİNANPAŞA",
    "MAHALLE": "AKÖREN, YILDIRIM BEYAZIT",
    "id": 1429
  },
  {
    "İL": "AFYONKARAHİSAR",
    "İLÇE": "SİNANPAŞA",
    "MAHALLE": "DÜZAĞAÇ, IŞIK",
    "id": 1430
  },
  {
    "İL": "AFYONKARAHİSAR",
    "İLÇE": "SİNANPAŞA",
    "MAHALLE": "FATİH",
    "id": 1431
  },
  {
    "İL": "AFYONKARAHİSAR",
    "İLÇE": "SİNANPAŞA",
    "MAHALLE": "AHMETPAŞA, GÖLCÜK",
    "id": 1432
  },
  {
    "İL": "AFYONKARAHİSAR",
    "İLÇE": "SİNANPAŞA",
    "MAHALLE": "KÜÇÜKHÜYÜK, KURTULUŞ",
    "id": 1433
  },
  {
    "İL": "AFYONKARAHİSAR",
    "İLÇE": "SİNANPAŞA",
    "MAHALLE": "TAŞOLUK, HÜRRİYET",
    "id": 1434
  },
  {
    "İL": "AFYONKARAHİSAR",
    "İLÇE": "SİNANPAŞA",
    "MAHALLE": "YUKARI",
    "id": 1435
  },
  {
    "İL": "AFYONKARAHİSAR",
    "İLÇE": "SİNANPAŞA",
    "MAHALLE": "ÇİĞİLTEPE",
    "id": 1436
  },
  {
    "İL": "AFYONKARAHİSAR",
    "İLÇE": "SİNANPAŞA",
    "MAHALLE": "DÜZAĞAÇ, FATİH",
    "id": 1437
  },
  {
    "İL": "AFYONKARAHİSAR",
    "İLÇE": "SİNANPAŞA",
    "MAHALLE": "KÜÇÜKHÜYÜK, ATATÜRK",
    "id": 1438
  },
  {
    "İL": "AFYONKARAHİSAR",
    "İLÇE": "SİNANPAŞA",
    "MAHALLE": "SERBAN, HİSAR",
    "id": 1439
  },
  {
    "İL": "AFYONKARAHİSAR",
    "İLÇE": "SİNANPAŞA",
    "MAHALLE": "TAŞOLUK, BAHÇELİEVLER",
    "id": 1440
  },
  {
    "İL": "AFYONKARAHİSAR",
    "İLÇE": "SİNANPAŞA",
    "MAHALLE": "TINAZTEPE, BAHÇELİEVLER",
    "id": 1441
  },
  {
    "İL": "AFYONKARAHİSAR",
    "İLÇE": "SİNANPAŞA",
    "MAHALLE": "TINAZTEPE, FATİH",
    "id": 1442
  },
  {
    "İL": "AFYONKARAHİSAR",
    "İLÇE": "SİNANPAŞA",
    "MAHALLE": "AKPINAR",
    "id": 1443
  },
  {
    "İL": "AFYONKARAHİSAR",
    "İLÇE": "SİNANPAŞA",
    "MAHALLE": "SERBAN, HOZMAN",
    "id": 1444
  },
  {
    "İL": "AFYONKARAHİSAR",
    "İLÇE": "SİNANPAŞA",
    "MAHALLE": "KILIÇARSLAN, ATATÜRK",
    "id": 1445
  },
  {
    "İL": "AFYONKARAHİSAR",
    "İLÇE": "SİNANPAŞA",
    "MAHALLE": "KIRKA, FATİH",
    "id": 1446
  },
  {
    "İL": "AFYONKARAHİSAR",
    "İLÇE": "SİNANPAŞA",
    "MAHALLE": "SERBAN, KÖPRÜBAŞI",
    "id": 1447
  },
  {
    "İL": "AFYONKARAHİSAR",
    "İLÇE": "SİNANPAŞA",
    "MAHALLE": "KILIÇARSLAN, KOCATEPE",
    "id": 1448
  },
  {
    "İL": "AFYONKARAHİSAR",
    "İLÇE": "SİNANPAŞA",
    "MAHALLE": "AHMETPAŞA, YUKARI",
    "id": 1449
  },
  {
    "İL": "AFYONKARAHİSAR",
    "İLÇE": "SİNANPAŞA",
    "MAHALLE": "SERBAN, CUMHURİYET",
    "id": 1450
  },
  {
    "İL": "AFYONKARAHİSAR",
    "İLÇE": "SİNANPAŞA",
    "MAHALLE": "SERBAN, ORTA",
    "id": 1451
  },
  {
    "İL": "AFYONKARAHİSAR",
    "İLÇE": "SİNANPAŞA",
    "MAHALLE": "TAŞOLUK, ÇINARLI",
    "id": 1452
  },
  {
    "İL": "AFYONKARAHİSAR",
    "İLÇE": "SİNANPAŞA",
    "MAHALLE": "TINAZTEPE, AMBAR",
    "id": 1453
  },
  {
    "İL": "AFYONKARAHİSAR",
    "İLÇE": "HOCALAR",
    "MAHALLE": "YENİ",
    "id": 1454
  },
  {
    "İL": "AFYONKARAHİSAR",
    "İLÇE": "HOCALAR",
    "MAHALLE": "ŞAFAK",
    "id": 1455
  },
  {
    "İL": "AFYONKARAHİSAR",
    "İLÇE": "HOCALAR",
    "MAHALLE": "HÜRRİYET",
    "id": 1456
  }
]